log_writer/__init__.py
log_writer/logger.py
log_writer-1.0.2.dist-info/METADATA
log_writer-1.0.2.dist-info/WHEEL
log_writer-1.0.2.dist-info/top_level.txt
log_writer-1.0.2.dist-info/RECORD
